Metadata-Version: 2.1
Name: vehiclemapperscript
Version: 50.0
Summary: Vehicle Mapper
Home-page: UNKNOWN
Author: yzcop
Author-email: yadugkrishnan@gmail.com
License: MIT
Platform: UNKNOWN
